setup.py
src/serval/__init__.py
src/serval/builtin.py
src/serval/interpreter.py
src/serval/lexer.py
src/serval/model.py
src/serval/parser.py
src/serval/scope.py
src/serval/tokens.py
src/serval.egg-info/PKG-INFO
src/serval.egg-info/SOURCES.txt
src/serval.egg-info/dependency_links.txt
src/serval.egg-info/entry_points.txt
src/serval.egg-info/not-zip-safe
src/serval.egg-info/requires.txt
src/serval.egg-info/top_level.txt
src/serval/expression/__init__.py
src/serval/expression/assignment.py
src/serval/expression/binding.py
src/serval/expression/conditional.py
src/serval/expression/definition.py
src/serval/expression/lambdaexpr.py
src/serval/expression/procedure.py
src/serval/expression/quote.py
src/serval/expression/selfeval.py
src/serval/expression/sequence.py
src/serval/expression/util.py
src/serval/expression/variable.py
src/serval/tests/__init__.py
src/serval/tests/test_interpreter.py
src/serval/tests/test_lexer.py
src/serval/tests/test_parser.py
src/serval/tests/test_the_little_schemer.py