Metadata-Version: 1.0
Name: serval
Version: 0.1
Summary: Simple Scheme interpreter in Python
Home-page: http://github.com/rspivak/serval
Author: Ruslan Spivak
Author-email: ruslan.spivak@gmail.com
License: MIT
Platform: UNKNOWN
Classifier: Intended Audience :: Developers
Classifier: License :: OSI Approved :: MIT License
Classifier: Programming Language :: Python
Classifier: Topic :: Software Development :: Interpreters
Classifier: Operating System :: Unix
